model/__init__.py
model/birch_clustering_model.py
model/doc2vec_model.py
model/feature_builder.py
model/lda_model.py
preprocessing/__init__.py
preprocessing/preprocessing.py
preprocessing/text_preprocessing.py
topic_modeling_twitter-0.0.1.2.dist-info/LICENSE
topic_modeling_twitter-0.0.1.2.dist-info/METADATA
topic_modeling_twitter-0.0.1.2.dist-info/WHEEL
topic_modeling_twitter-0.0.1.2.dist-info/top_level.txt
topic_modeling_twitter-0.0.1.2.dist-info/RECORD
