Metadata-Version: 2.1
Name: topic-modeling-twitter
Version: 0.0.1.2
Summary: a package with topic-modeling solutions for twitter data
Home-page: https://github.com/pypa/sampleproject
Author: Parisa Zahedi
Author-email: p.zahedi@uu.nl
License: UNKNOWN
Platform: UNKNOWN
Classifier: Programming Language :: Python :: 3
Classifier: License :: OSI Approved :: MIT License
Classifier: Operating System :: OS Independent
Requires-Python: >=3.6
